{
  "list": [
    {
      "id": "2b39e1cd-a489-49b0-b6a7-3c51f339b186",
      "desc": "do homeowork",
      "created": "2021-10-02T20:55:50.328Z",
      "status": "unchecked",
      "alarm": 0,
      "tag": "priority"
    },
    {
      "id": "c400c29c-177b-41fc-937d-0bad134994bf",
      "desc": "hihi normal",
      "created": "2021-10-02T20:59:08.012Z",
      "status": "unchecked",
      "alarm": 0,
      "tag": "normal"
    },
    {
      "id": "d302bfad-953d-46ad-ba02-9c1491af00b5",
      "desc": "very important",
      "created": "2021-10-03T22:16:05.981Z",
      "status": "unchecked",
      "alarm": 0,
      "tag": "important"
    },
    {
      "id": "074ac108-567f-4ef4-951b-e8dd34c837cc",
      "desc": "finish this task edit",
      "created": "2021-10-04T19:17:01.788Z",
      "status": "unchecked",
      "alarm": 0,
      "tag": "normal"
    },
    {
      "id": "e23d1f49-0e34-467e-81d5-d86b3e4308ef",
      "desc": "nono ononod well caster heafverne",
      "created": "2021-10-04T19:18:36.300Z",
      "status": "unchecked",
      "alarm": 10,
      "tag": "normal"
    },
    {
      "id": "dad4777e-b693-4c4f-b81a-8f6d31eb6c66",
      "desc": "very very important",
      "created": "2021-10-04T19:19:00.204Z",
      "status": "unchecked",
      "alarm": 0,
      "tag": "important"
    },
    {
      "id": "979f02a7-f63d-4175-8d27-91434fc21e65",
      "desc": "i love you",
      "created": "2021-10-04T20:29:19.752Z",
      "status": "unchecked",
      "alarm": 0.16666666666666666,
      "tag": "hobby"
    },
    {
      "id": "7218b6b3-d914-4b71-b301-da4348ecdd0f",
      "desc": "pipip",
      "created": "2021-10-04T19:42:42.281Z",
      "status": "unchecked",
      "alarm": 0,
      "tag": "priority"
    },
    {
      "id": "a151dcd6-8c18-40e3-a3c0-fb7694dd2eb7",
      "desc": "tank",
      "created": "2021-10-04T20:29:06.434Z",
      "status": "unchecked",
      "alarm": 10,
      "tag": "hobby"
    },
    {
      "id": "5800d0f8-8361-4ae7-bb8b-4f8075126f19",
      "desc": "fish",
      "created": "2021-10-04T20:30:59.451Z",
      "status": "unchecked",
      "alarm": 10.766666666666666,
      "tag": "hobby"
    }
  ],
  "tags": [
    {
      "id": "48192723-3f5f-4e60-85d5-d63910de1061",
      "name": "priority"
    },
    {
      "id": "97fa5958-4b0d-4135-8cab-38bc7f979319",
      "name": "normal"
    },
    {
      "id": "369e21fb-3d2f-4771-874c-a0b5a222bbf0",
      "name": "important"
    },
    {
      "id": "ed2d9d62-38d5-4fbe-8f6f-191dfe58cfe4",
      "name": "hobby"
    }
  ]
}